plsconvert/__init__.py
plsconvert/cli.py
plsconvert/graph_analysis.py
plsconvert/graph_representation.py
plsconvert/converters/.README.md
plsconvert/converters/__init__.py
plsconvert/converters/abstract.py
plsconvert/converters/progressbar.py
plsconvert/converters/registry.py
plsconvert/converters/universal.py
plsconvert/converters/addons/ai.py
plsconvert/converters/addons/audio.py
plsconvert/converters/addons/braille.py
plsconvert/converters/addons/compression.py
plsconvert/converters/addons/configs.py
plsconvert/converters/addons/docs.py
plsconvert/converters/addons/media.py
plsconvert/converters/addons/threed.py
plsconvert/utils/dependency.py
plsconvert/utils/errors.py
plsconvert/utils/files.py
plsconvert/utils/graph.py
plsconvert-0.1.7.dist-info/METADATA
plsconvert-0.1.7.dist-info/WHEEL
plsconvert-0.1.7.dist-info/entry_points.txt
plsconvert-0.1.7.dist-info/licenses/LICENSE
plsconvert-0.1.7.dist-info/RECORD
