Metadata-Version: 2.4
Name: plsconvert
Version: 0.1.7
Summary: Convert any file to any other.
Project-URL: Homepage, https://github.com/ThorTuwy/plsconvert
Project-URL: Bug Tracker, https://github.com/ThorTuwy/plsconvert/issues
Author-email: ThorTuwy <tuwy@tuwy.win>, Víctor <victordlp8@gmail.com>
License-File: LICENSE
Requires-Python: >=3.13
Requires-Dist: halo>=0.0.31
Requires-Dist: tqdm>=4.67.1
Provides-Extra: 3d
Requires-Dist: imageio-ffmpeg>=0.5.1; extra == '3d'
Requires-Dist: imageio>=2.36.1; extra == '3d'
Requires-Dist: moderngl>=5.12.0; extra == '3d'
Requires-Dist: pillow>=11.3.0; extra == '3d'
Requires-Dist: pygltflib>=1.16.3; extra == '3d'
Requires-Dist: pyrr>=0.10.3; extra == '3d'
Requires-Dist: trimesh>=4.5.1; extra == '3d'
Provides-Extra: ai
Requires-Dist: onnxruntime>=1.22.1; extra == 'ai'
Requires-Dist: pillow>=11.3.0; extra == 'ai'
Requires-Dist: rapidocr>=3.2.0; extra == 'ai'
Provides-Extra: all
Requires-Dist: imageio-ffmpeg>=0.5.1; extra == 'all'
Requires-Dist: imageio>=2.36.1; extra == 'all'
Requires-Dist: matplotlib>=3.10.3; extra == 'all'
Requires-Dist: midi2audio>=0.1.1; extra == 'all'
Requires-Dist: moderngl>=5.12.0; extra == 'all'
Requires-Dist: onnxruntime>=1.22.1; extra == 'all'
Requires-Dist: openpyxl>=3.1.5; extra == 'all'
Requires-Dist: pandas>=2.3.1; extra == 'all'
Requires-Dist: pdf2docx>=0.5.8; extra == 'all'
Requires-Dist: pillow>=11.3.0; extra == 'all'
Requires-Dist: pygltflib>=1.16.3; extra == 'all'
Requires-Dist: pyrr>=0.10.3; extra == 'all'
Requires-Dist: pyttsx3>=2.99; extra == 'all'
Requires-Dist: pyyaml>=6.0.2; extra == 'all'
Requires-Dist: rapidocr>=3.2.0; extra == 'all'
Requires-Dist: scipy>=1.16.0; extra == 'all'
Requires-Dist: tomlkit>=0.13.3; extra == 'all'
Requires-Dist: trimesh>=4.5.1; extra == 'all'
Provides-Extra: audio
Requires-Dist: matplotlib>=3.10.3; extra == 'audio'
Requires-Dist: midi2audio>=0.1.1; extra == 'audio'
Requires-Dist: pyttsx3>=2.99; extra == 'audio'
Requires-Dist: scipy>=1.16.0; extra == 'audio'
Provides-Extra: config
Requires-Dist: pyyaml>=6.0.2; extra == 'config'
Requires-Dist: tomlkit>=0.13.3; extra == 'config'
Provides-Extra: dev
Requires-Dist: imageio-ffmpeg>=0.5.1; extra == 'dev'
Requires-Dist: imageio>=2.36.1; extra == 'dev'
Requires-Dist: matplotlib>=3.10.3; extra == 'dev'
Requires-Dist: midi2audio>=0.1.1; extra == 'dev'
Requires-Dist: moderngl>=5.12.0; extra == 'dev'
Requires-Dist: netgraph>=4.13.2; extra == 'dev'
Requires-Dist: networkx>=3.0; extra == 'dev'
Requires-Dist: onnxruntime>=1.22.1; extra == 'dev'
Requires-Dist: openpyxl>=3.1.5; extra == 'dev'
Requires-Dist: pandas>=2.3.1; extra == 'dev'
Requires-Dist: pdf2docx>=0.5.8; extra == 'dev'
Requires-Dist: pillow>=11.3.0; extra == 'dev'
Requires-Dist: pygltflib>=1.16.3; extra == 'dev'
Requires-Dist: pyrr>=0.10.3; extra == 'dev'
Requires-Dist: pyttsx3>=2.99; extra == 'dev'
Requires-Dist: pyyaml>=6.0.2; extra == 'dev'
Requires-Dist: rapidocr>=3.2.0; extra == 'dev'
Requires-Dist: scipy>=1.16.0; extra == 'dev'
Requires-Dist: tomlkit>=0.13.3; extra == 'dev'
Requires-Dist: trimesh>=4.5.1; extra == 'dev'
Provides-Extra: docs
Requires-Dist: openpyxl>=3.1.5; extra == 'docs'
Requires-Dist: pandas>=2.3.1; extra == 'docs'
Requires-Dist: pdf2docx>=0.5.8; extra == 'docs'
Provides-Extra: graph
Requires-Dist: matplotlib>=3.10.3; extra == 'graph'
Requires-Dist: netgraph>=4.13.2; extra == 'graph'
Requires-Dist: networkx>=3.0; extra == 'graph'
Provides-Extra: noai
Requires-Dist: matplotlib>=3.10.3; extra == 'noai'
Requires-Dist: midi2audio>=0.1.1; extra == 'noai'
Requires-Dist: openpyxl>=3.1.5; extra == 'noai'
Requires-Dist: pandas>=2.3.1; extra == 'noai'
Requires-Dist: pdf2docx>=0.5.8; extra == 'noai'
Requires-Dist: pyttsx3>=2.99; extra == 'noai'
Requires-Dist: pyyaml>=6.0.2; extra == 'noai'
Requires-Dist: scipy>=1.16.0; extra == 'noai'
Requires-Dist: tomlkit>=0.13.3; extra == 'noai'
